slack/__init__.py
slack/post.py
slackbot/__init__.py
slackbot/post.py
slackbot_jucho-0.2.1.dist-info/LICENSE
slackbot_jucho-0.2.1.dist-info/METADATA
slackbot_jucho-0.2.1.dist-info/WHEEL
slackbot_jucho-0.2.1.dist-info/top_level.txt
slackbot_jucho-0.2.1.dist-info/RECORD
