Metadata-Version: 2.1
Name: slackbot-jucho
Version: 0.2.1
Summary: slackbot bot
Home-page: https://https://github.com/jucho2725/slackbot_jucho
Author: jinuk.cho
Author-email: cju2725@gmail.com
License: UNKNOWN
Download-URL: https://github.com/jucho2725/slackbot_jucho/archive/master.zip
Keywords: slackbot bot
Platform: UNKNOWN
Classifier: Programming Language :: Python :: 3
Classifier: Programming Language :: Python :: 3.2
Classifier: Programming Language :: Python :: 3.3
Classifier: Programming Language :: Python :: 3.4
Classifier: Programming Language :: Python :: 3.5
Classifier: Programming Language :: Python :: 3.6
Classifier: Programming Language :: Python :: 3.7
Requires-Python: >=3.3
Requires-Dist: slackclient (==2.9.3)
